odoo8_addon_product_uom_unece-8.0.0.1.0-py2.7-nspkg.pth
odoo_addons/product_uom_unece/__openerp__.py
odoo_addons/product_uom_unece/__init__.py
odoo_addons/product_uom_unece/README.rst
odoo_addons/product_uom_unece/models/__init__.py
odoo_addons/product_uom_unece/models/product_uom.py
odoo_addons/product_uom_unece/views/product_uom.xml
odoo_addons/product_uom_unece/data/unece.xml
odoo8_addon_product_uom_unece-8.0.0.1.0.dist-info/top_level.txt
odoo8_addon_product_uom_unece-8.0.0.1.0.dist-info/WHEEL
odoo8_addon_product_uom_unece-8.0.0.1.0.dist-info/RECORD
odoo8_addon_product_uom_unece-8.0.0.1.0.dist-info/metadata.json
odoo8_addon_product_uom_unece-8.0.0.1.0.dist-info/DESCRIPTION.rst
odoo8_addon_product_uom_unece-8.0.0.1.0.dist-info/METADATA
odoo8_addon_product_uom_unece-8.0.0.1.0.dist-info/namespace_packages.txt
